{
  "rule_id": "mumbai_dcpr_table_54_row_6",
  "title": "Table 54 - Row 6",
  "jurisdiction": "mumbai_dcpr",
  "version": "extracted_from_docx",
  "clause_number": "Table-54.6",
  "clause_text": "Sr No: I | Areas: Island City | Areas: Island City | Zone: Resid ential /Com merci al | Road width: 27 m and above | Zonal (Basic ): 1.33 | Additio nal FSI on payme nt of Premiu m: 0.84 | Adm issib le TDR: 0.8 3 | Permi ssibl e FSI (4+5 +6): 3.0",
  "parsed": {
    "type": "table",
    "table_data": {
      "headers": [
        "Sr No",
        "Areas",
        "Areas",
        "Zone",
        "Road width",
        "Zonal (Basic )",
        "Additio nal FSI on payme nt of Premiu m",
        "Adm issib le TDR",
        "Permi ssibl e FSI (4+5 +6)"
      ],
      "values": [
        "I",
        "Island City",
        "Island City",
        "Resid ential /Com merci al",
        "27 m and above",
        "1.33",
        "0.84",
        "0.8 3",
        "3.0"
      ]
    }
  },
  "examples": [],
  "ambiguous": false,
  "ambiguity_reason": null,
  "source_pdf": {
    "filename": "MUBAI-DCPR.docx",
    "page": "table_54",
    "text_snippet": "Sr No: I | Areas: Island City | Areas: Island City | Zone: Resid ential /Com merci al | Road width: 27 m and above | Zonal (Basic ): 1.33 | Additio nal FSI on payme nt of Premiu m: 0.84 | Adm issib le"
  },
  "created_at": "2025-11-19T00:14:48.369023",
  "extraction_method": "docx_table",
  "approved_at": "2025-11-19T00:15:26.573798",
  "approved_by": "auto_approve_script",
  "verification_status": "auto_approved"
}